Lab IV/stack.v
module stack (rstN, clk, data_in, push, pop, data_out, full, empty);

	parameter DEPTH = 8;
	parameter WIDTH	= 4;
    
	input wire rstN, push, pop, clk;
	input wire [WIDTH - 1 : 0] data_in;
	output full, empty;
	output reg [WIDTH - 1 : 0] data_out;
    
	reg [WIDTH - 1 : 0] stack [0 : DEPTH - 1];
	reg [DEPTH : 0] hotbit_address;
	
    
	assign	empty = !hotbit_address[0];
	assign	full  = hotbit_address[DEPTH];
	integer i;

	always @(posedge clk) begin
		if (!rstN) begin
			for (i = 0 ; i < DEPTH ; i = i +1) begin
				stack[i] = {WIDTH{1'b0}};
			end
			hotbit_address = {{DEPTH-1{1'b0}}, 1'b1};
		end
		else begin
			if (push &&  !full) begin
				for ( i = 0 ; i < DEPTH; i = i+ 1) begin
					if (hotbit_address[i]) stack[i] = data_in;
				end
				hotbit_address = hotbit_address << 1;
			end
			else if (pop && empty) begin
				for ( i = 1 ; i <= DEPTH ; i = i +1) begin
					if(hotbit_address[i]) data_out = stack[i-1];
				end
				hotbit_address = hotbit_address >> 1;	
			end
		end
	end
endmodule

Lab IV/stack_tb.v
`include "stack.v"
`timescale 1ns/1ns
module stack_tb;

	parameter cycle = 10;
	reg	rstN, push, pop, clk;
	reg	[3 : 0] data_in;
	wire full, empty;
	wire [3 : 0] data_out;
	integer i;
	
	stack #(.DEPTH(8),.WIDTH(4)) stack0 (
		.rstN(rstN),
		.clk(clk),
		.data_in(data_in),
		.push(push),
		.pop(pop),
		.data_out(data_out),
		.full(full),
		.empty(empty));
    
	initial begin
		clk	= 0;
		forever	#(cycle/2) clk = ~clk;
	end
    
	initial begin
		$monitor($time,"\tpush=%b, pop=%b, data_in=%d, empty=%b, full=%b, data_out=%d", push, pop, data_in, empty, full, data_out);
		$dumpfile("stack.vcd");
		$dumpvars(0,stack0);
		rstN = 0;
		push = 0;
		pop = 0;
		data_in = 0;
		#cycle rstN = 1;
  
		for (i = 1; i <= 8; i = i +1) begin
		#cycle push = 1;
		pop = 0;
		data_in = i;
		end
		
		#cycle data_in = 9;
		
		#cycle push = 0;
		pop = 1;
		for (i = 0; i <= 8; i = i + 1) begin
			#cycle ;
		end
		
		#cycle push = 1;
		data_in = 1;
		#cycle data_in = 2;
		#cycle push = 0;
		$finish;            
	end    
endmodule

Lab IV/stack.vcd
$date
	Sun Jul 16 13:12:18 2023
$end
$version
	Icarus Verilog
$end
$timescale
	1ns
$end
$scope module stack_tb $end
$scope module stack0 $end
$var wire 1 ! clk $end
$var wire 4 " data_in [3:0] $end
$var wire 1 # pop $end
$var wire 1 $ push $end
$var wire 1 % rstN $end
$var wire 1 & full $end
$var wire 1 ' empty $end
$var parameter 32 ( DEPTH $end
$var parameter 32 ) WIDTH $end
$var reg 4 * data_out [3:0] $end
$var reg 9 + hotbit_address [8:0] $end
$var integer 32 , i [31:0] $end
$upscope $end
$upscope $end
$enddefinitions $end
$comment Show the parameter values. $end
$dumpall
b100 )
b1000 (
$end
#0
$dumpvars
bx ,
bx +
bx *
x'
x&
0%
0$
0#
b0 "
0!
$end
#5
0'
0&
b1 +
b1000 ,
1!
#10
0!
1%
#15
1!
#20
0!
b1 "
1$
#25
1'
b10 +
b1000 ,
1!
#30
0!
b10 "
#35
b100 +
b1000 ,
1!
#40
0!
b11 "
#45
b1000 +
b1000 ,
1!
#50
0!
b100 "
#55
b10000 +
b1000 ,
1!
#60
0!
b101 "
#65
b100000 +
b1000 ,
1!
#70
0!
b110 "
#75
b1000000 +
b1000 ,
1!
#80
0!
b111 "
#85
b10000000 +
b1000 ,
1!
#90
0!
b1000 "
#95
1&
b100000000 +
b1000 ,
1!
#100
0!
b1001 "
#105
1!
#110
0!
1#
0$
#115
0&
b10000000 +
b1000 *
b1001 ,
1!
#120
0!
#125
b1000000 +
b111 *
b1001 ,
1!
#130
0!
#135
b100000 +
b110 *
b1001 ,
1!
#140
0!
#145
b10000 +
b101 *
b1001 ,
1!
#150
0!
#155
b1000 +
b100 *
b1001 ,
1!
#160
0!
#165
b100 +
b11 *
b1001 ,
1!
#170
0!
#175
b10 +
b10 *
b1001 ,
1!
#180
0!
#185
0'
b1 +
b1 *
b1001 ,
1!
#190
0!
#195
1!
#200
0!
#205
1!
#210
0!
b1 "
1$
#215
1'
b10 +
b1000 ,
1!
#220
0!
b10 "
#225
b100 +
b1000 ,
1!
#230
0!
0$
